{
  "meta": {
    "fontName": "Vergil Regular",
    "file": "Vergil-Regular.ttf",
    "upm": 2048,
    "zones": 9,
    "zoneHeight": 271.1,
    "yBottom": -650,
    "yTop": 1790
  },
  "glyphs": {
    ".notdef": {
      "name": ".notdef",
      "unicode": null,
      "unicodeHex": null,
      "char": ".notdef",
      "advanceWidth": 1220,
      "left": [
        227,
        227,
        227,
        227,
        227,
        227,
        227,
        227,
        227
      ],
      "right": [
        220,
        220,
        220,
        220,
        220,
        220,
        220,
        220,
        220
      ],
      "leftUnweighted": [
        227,
        227,
        227,
        227,
        227,
        227,
        227,
        227,
        227
      ],
      "rightUnweighted": [
        220,
        220,
        220,
        220,
        220,
        220,
        220,
        220,
        220
      ]
    },
    "A": {
      "name": "A",
      "unicode": 65,
      "unicodeHex": "U+0041",
      "char": "A",
      "advanceWidth": 1574,
      "left": [
        -1,
        -1,
        81.8,
        190.2,
        298.6,
        407,
        515.4,
        623.8,
        -1
      ],
      "right": [
        -1,
        -1,
        92.6,
        201,
        309.4,
        417.8,
        526.2,
        634.6,
        -1
      ],
      "leftUnweighted": [
        -1,
        -1,
        81.8,
        260.2,
        363.3,
        465.1,
        566,
        666.8,
        -1
      ],
      "rightUnweighted": [
        -1,
        -1,
        92.6,
        292.1,
        388.5,
        483.6,
        579.8,
        675.1,
        -1
      ]
    },
    "B": {
      "name": "B",
      "unicode": 66,
      "unicodeHex": "U+0042",
      "char": "B",
      "advanceWidth": 1324,
      "left": [
        -1,
        -1,
        71.9,
        180.3,
        233,
        233,
        233,
        127.7,
        -1
      ],
      "right": [
        -1,
        -1,
        235.5,
        127.1,
        138.9,
        247.3,
        209.1,
        290.8,
        -1
      ],
      "leftUnweighted": [
        -1,
        -1,
        71.9,
        232.1,
        233,
        233,
        233,
        127.7,
        -1
      ],
      "rightUnweighted": [
        -1,
        -1,
        330.4,
        127.1,
        138.9,
        319.1,
        209.1,
        290.8,
        -1
      ]
    },
    "C": {
      "name": "C",
      "unicode": 67,
      "unicodeHex": "U+0043",
      "char": "C",
      "advanceWidth": 1581,
      "left": [
        -1,
        -1,
        352.8,
        244.4,
        136.8,
        125.9,
        204,
        312.4,
        -1
      ],
      "right": [
        -1,
        -1,
        251,
        142.6,
        251,
        359.4,
        210.4,
        270.6,
        -1
      ],
      "leftUnweighted": [
        -1,
        -1,
        496.5,
        244.4,
        136.8,
        125.9,
        204,
        464.2,
        -1
      ],
      "rightUnweighted": [
        -1,
        -1,
        267,
        142.6,
        1192.2,
        1228.2,
        210.4,
        270.6,
        -1
      ]
    },
    "D": {
      "name": "D",
      "unicode": 68,
      "unicodeHex": "U+0044",
      "char": "D",
      "advanceWidth": 1687,
      "left": [
        -1,
        -1,
        77.5,
        185.9,
        233,
        233,
        233,
        127.7,
        -1
      ],
      "right": [
        -1,
        -1,
        357.1,
        248.7,
        140.3,
        124.6,
        193.9,
        302.3,
        -1
      ],
      "leftUnweighted": [
        -1,
        -1,
        77.5,
        232.4,
        233,
        233,
        233,
        127.7,
        -1
      ],
      "rightUnweighted": [
        -1,
        -1,
        554.6,
        262.5,
        140.3,
        124.6,
        193.9,
        436.1,
        -1
      ]
    },
    "E": {
      "name": "E",
      "unicode": 69,
      "unicodeHex": "U+0045",
      "char": "E",
      "advanceWidth": 1362,
      "left": [
        -1,
        -1,
        71.9,
        180.3,
        233,
        233,
        233,
        123.9,
        -1
      ],
      "right": [
        -1,
        -1,
        166,
        182.1,
        290.5,
        398.9,
        507.3,
        261.7,
        -1
      ],
      "leftUnweighted": [
        -1,
        -1,
        71.9,
        232.1,
        233,
        233,
        233,
        123.9,
        -1
      ],
      "rightUnweighted": [
        -1,
        -1,
        166,
        182.1,
        614.6,
        401,
        579.3,
        261.7,
        -1
      ]
    },
    "F": {
      "name": "F",
      "unicode": 70,
      "unicodeHex": "U+0046",
      "char": "F",
      "advanceWidth": 1148,
      "left": [
        -1,
        -1,
        77.5,
        185.9,
        233,
        233,
        233,
        123.9,
        -1
      ],
      "right": [
        -1,
        -1,
        512.2,
        403.8,
        295.4,
        187,
        156.1,
        47.7,
        -1
      ],
      "leftUnweighted": [
        -1,
        -1,
        77.5,
        232.4,
        233,
        233,
        233,
        123.9,
        -1
      ],
      "rightUnweighted": [
        -1,
        -1,
        565.5,
        720.4,
        400.6,
        187,
        365.3,
        47.7,
        -1
      ]
    },
    "G": {
      "name": "G",
      "unicode": 71,
      "unicodeHex": "U+0047",
      "char": "G",
      "advanceWidth": 1639,
      "left": [
        -1,
        -1,
        352.8,
        244.4,
        136.8,
        125.9,
        204,
        312.4,
        -1
      ],
      "right": [
        -1,
        -1,
        346.4,
        238,
        190,
        298.4,
        406.8,
        328.7,
        -1
      ],
      "leftUnweighted": [
        -1,
        -1,
        496.5,
        244.4,
        136.8,
        125.9,
        204,
        464.2,
        -1
      ],
      "rightUnweighted": [
        -1,
        -1,
        393,
        238,
        190,
        934.4,
        467.9,
        328.7,
        -1
      ]
    },
    "H": {
      "name": "H",
      "unicode": 72,
      "unicodeHex": "U+0048",
      "char": "H",
      "advanceWidth": 1760,
      "left": [
        -1,
        -1,
        77.5,
        185.9,
        233,
        233,
        233,
        127.7,
        -1
      ],
      "right": [
        -1,
        -1,
        77.5,
        185.9,
        233,
        233,
        233,
        127.7,
        -1
      ],
      "leftUnweighted": [
        -1,
        -1,
        77.5,
        232.4,
        233,
        233,
        233,
        127.7,
        -1
      ],
      "rightUnweighted": [
        -1,
        -1,
        77.5,
        232.4,
        233,
        233,
        233,
        127.7,
        -1
      ]
    },
    "I": {
      "name": "I",
      "unicode": 73,
      "unicodeHex": "U+0049",
      "char": "I",
      "advanceWidth": 660,
      "left": [
        -1,
        -1,
        77.5,
        185.9,
        233,
        233,
        233,
        127.7,
        -1
      ],
      "right": [
        -1,
        -1,
        77.5,
        185.9,
        233,
        233,
        233,
        127.7,
        -1
      ],
      "leftUnweighted": [
        -1,
        -1,
        77.5,
        232.4,
        233,
        233,
        233,
        127.7,
        -1
      ],
      "rightUnweighted": [
        -1,
        -1,
        77.5,
        232.4,
        233,
        233,
        233,
        127.7,
        -1
      ]
    },
    "J": {
      "name": "J",
      "unicode": 74,
      "unicodeHex": "U+004A",
      "char": "J",
      "advanceWidth": 626,
      "left": [
        -101.9,
        6.5,
        114.9,
        223.3,
        233,
        233,
        233,
        127.7,
        -1
      ],
      "right": [
        373.8,
        265.4,
        210.1,
        199,
        199,
        199,
        199,
        93.7,
        -1
      ],
      "leftUnweighted": [
        -101.9,
        227.3,
        233,
        233,
        233,
        233,
        233,
        127.7,
        -1
      ],
      "rightUnweighted": [
        389.1,
        265.4,
        210.1,
        199,
        199,
        199,
        199,
        93.7,
        -1
      ]
    },
    "K": {
      "name": "K",
      "unicode": 75,
      "unicodeHex": "U+004B",
      "char": "K",
      "advanceWidth": 1451,
      "left": [
        -1,
        -1,
        77.5,
        185.9,
        233,
        233,
        233,
        127.7,
        -1
      ],
      "right": [
        -1,
        -1,
        58.6,
        167,
        275.4,
        383.8,
        492.2,
        240.4,
        -1
      ],
      "leftUnweighted": [
        -1,
        -1,
        77.5,
        232.4,
        233,
        233,
        233,
        127.7,
        -1
      ],
      "rightUnweighted": [
        -1,
        -1,
        58.6,
        296.1,
        544.1,
        730.3,
        542,
        240.4,
        -1
      ]
    },
    "L": {
      "name": "L",
      "unicode": 76,
      "unicodeHex": "U+004C",
      "char": "L",
      "advanceWidth": 1365,
      "left": [
        -1,
        -1,
        77.5,
        185.9,
        233,
        233,
        233,
        127.7,
        -1
      ],
      "right": [
        -1,
        -1,
        169,
        185.1,
        293.5,
        401.9,
        510.3,
        618.7,
        -1
      ],
      "leftUnweighted": [
        -1,
        -1,
        77.5,
        232.4,
        233,
        233,
        233,
        127.7,
        -1
      ],
      "rightUnweighted": [
        -1,
        -1,
        169,
        185.1,
        938,
        938,
        938,
        832.7,
        -1
      ]
    },
    "M": {
      "name": "M",
      "unicode": 77,
      "unicodeHex": "U+004D",
      "char": "M",
      "advanceWidth": 2026,
      "left": [
        -1,
        -1,
        98.3,
        206.7,
        242.6,
        253.9,
        265.2,
        161.6,
        -1
      ],
      "right": [
        -1,
        -1,
        77.5,
        185.9,
        233,
        233,
        233,
        233,
        -1
      ],
      "leftUnweighted": [
        -1,
        -1,
        98.3,
        230.8,
        242.6,
        253.9,
        265.2,
        161.6,
        -1
      ],
      "rightUnweighted": [
        -1,
        -1,
        77.5,
        232.4,
        233,
        233,
        233,
        233,
        -1
      ]
    },
    "N": {
      "name": "N",
      "unicode": 78,
      "unicodeHex": "U+004E",
      "char": "N",
      "advanceWidth": 1757,
      "left": [
        -1,
        -1,
        108.8,
        217.2,
        238,
        238,
        238,
        125.9,
        -1
      ],
      "right": [
        -1,
        -1,
        312.4,
        204,
        204,
        204,
        204,
        116.5,
        -1
      ],
      "leftUnweighted": [
        -1,
        -1,
        108.8,
        237.4,
        238,
        238,
        238,
        125.9,
        -1
      ],
      "rightUnweighted": [
        -1,
        -1,
        488.9,
        204,
        204,
        204,
        204,
        116.5,
        -1
      ]
    },
    "O": {
      "name": "O",
      "unicode": 79,
      "unicodeHex": "U+004F",
      "char": "O",
      "advanceWidth": 1794,
      "left": [
        -1,
        -1,
        351,
        242.6,
        136.1,
        126.3,
        205.6,
        314,
        -1
      ],
      "right": [
        -1,
        -1,
        357,
        248.6,
        140.2,
        124.5,
        193.2,
        301.6,
        -1
      ],
      "leftUnweighted": [
        -1,
        -1,
        496.5,
        242.6,
        136.1,
        126.3,
        205.6,
        463.8,
        -1
      ],
      "rightUnweighted": [
        -1,
        -1,
        539.2,
        259.4,
        140.2,
        124.5,
        193.2,
        427.7,
        -1
      ]
    },
    "P": {
      "name": "P",
      "unicode": 80,
      "unicodeHex": "U+0050",
      "char": "P",
      "advanceWidth": 1162,
      "left": [
        -1,
        -1,
        105,
        213.4,
        233,
        233,
        233,
        146.6,
        -1
      ],
      "right": [
        -1,
        -1,
        433.3,
        324.9,
        216.5,
        108.1,
        59.7,
        168.1,
        -1
      ],
      "leftUnweighted": [
        -1,
        -1,
        105,
        232.3,
        233,
        233,
        233,
        146.6,
        -1
      ],
      "rightUnweighted": [
        -1,
        -1,
        607,
        734.3,
        531.4,
        108.1,
        59.7,
        223,
        -1
      ]
    },
    "Q": {
      "name": "Q",
      "unicode": 81,
      "unicodeHex": "U+0051",
      "char": "Q",
      "advanceWidth": 1794,
      "left": [
        567,
        458.6,
        350.2,
        241.8,
        136.2,
        126.3,
        205.6,
        314,
        -1
      ],
      "right": [
        -575.8,
        -467.4,
        -359,
        -250.6,
        -142.2,
        -33.8,
        74.6,
        183,
        -1
      ],
      "leftUnweighted": [
        1651.7,
        1115.2,
        587.6,
        241.8,
        136.2,
        126.3,
        205.6,
        463.8,
        -1
      ],
      "rightUnweighted": [
        -575.8,
        237.7,
        532.8,
        260.3,
        140.5,
        124.5,
        193.2,
        427.7,
        -1
      ]
    },
    "R": {
      "name": "R",
      "unicode": 82,
      "unicodeHex": "U+0052",
      "char": "R",
      "advanceWidth": 1405,
      "left": [
        -1,
        -1,
        105,
        213.4,
        233,
        233,
        233,
        146.6,
        -1
      ],
      "right": [
        -1,
        -1,
        75.7,
        184.1,
        292.5,
        378.6,
        300.6,
        409,
        -1
      ],
      "leftUnweighted": [
        -1,
        -1,
        105,
        232.3,
        233,
        233,
        233,
        146.6,
        -1
      ],
      "rightUnweighted": [
        -1,
        -1,
        75.7,
        295.1,
        455.6,
        378.6,
        300.6,
        456.7,
        -1
      ]
    },
    "S": {
      "name": "S",
      "unicode": 83,
      "unicodeHex": "U+0053",
      "char": "S",
      "advanceWidth": 1098,
      "left": [
        -1,
        -1,
        166.2,
        241.6,
        326,
        217.6,
        109.2,
        195.4,
        303.8
      ],
      "right": [
        -1,
        -1,
        241.9,
        133.5,
        169.3,
        277.7,
        386.1,
        219.7,
        328.1
      ],
      "leftUnweighted": [
        -1,
        -1,
        166.2,
        241.6,
        580.4,
        241.6,
        109.2,
        195.4,
        429.5
      ],
      "rightUnweighted": [
        -1,
        -1,
        290.8,
        133.5,
        169.3,
        430.7,
        510.4,
        219.7,
        429.6
      ]
    },
    "T": {
      "name": "T",
      "unicode": 84,
      "unicodeHex": "U+0054",
      "char": "T",
      "advanceWidth": 1488,
      "left": [
        -1,
        -1,
        504.7,
        464.8,
        356.4,
        248,
        139.6,
        31.2,
        -1
      ],
      "right": [
        -1,
        -1,
        504.7,
        464.8,
        356.4,
        248,
        139.6,
        31.2,
        -1
      ],
      "leftUnweighted": [
        -1,
        -1,
        504.7,
        646.9,
        647,
        647,
        275.7,
        31.2,
        -1
      ],
      "rightUnweighted": [
        -1,
        -1,
        504.7,
        646.9,
        647,
        647,
        275.7,
        31.2,
        -1
      ]
    },
    "U": {
      "name": "U",
      "unicode": 85,
      "unicodeHex": "U+0055",
      "char": "U",
      "advanceWidth": 1451,
      "left": [
        -1,
        -1,
        330.8,
        222.4,
        194,
        194,
        194,
        98.1,
        -1
      ],
      "right": [
        -1,
        -1,
        330.2,
        221.8,
        186.1,
        186,
        186,
        110.6,
        -1
      ],
      "leftUnweighted": [
        -1,
        -1,
        406.3,
        222.4,
        194,
        194,
        194,
        98.1,
        -1
      ],
      "rightUnweighted": [
        -1,
        -1,
        406.9,
        221.8,
        186.1,
        186,
        186,
        110.6,
        -1
      ]
    },
    "V": {
      "name": "V",
      "unicode": 86,
      "unicodeHex": "U+0056",
      "char": "V",
      "advanceWidth": 1540,
      "left": [
        -1,
        -1,
        673.5,
        565.1,
        456.7,
        348.3,
        239.9,
        131.5,
        -1
      ],
      "right": [
        -1,
        -1,
        655.6,
        547.2,
        438.8,
        330.4,
        222,
        113.6,
        -1
      ],
      "leftUnweighted": [
        -1,
        -1,
        676.5,
        594.7,
        497.9,
        403.2,
        308.4,
        131.5,
        -1
      ],
      "rightUnweighted": [
        -1,
        -1,
        670,
        583.1,
        480,
        379.1,
        278.3,
        113.6,
        -1
      ]
    },
    "W": {
      "name": "W",
      "unicode": 87,
      "unicodeHex": "U+0057",
      "char": "W",
      "advanceWidth": 2209,
      "left": [
        -1,
        -1,
        602.6,
        535,
        454.9,
        348.7,
        240.3,
        131.9,
        -1
      ],
      "right": [
        -1,
        -1,
        559.2,
        493.5,
        415.4,
        331,
        222.6,
        114.2,
        -1
      ],
      "leftUnweighted": [
        -1,
        -1,
        602.6,
        535,
        454.9,
        376.4,
        298,
        131.9,
        -1
      ],
      "rightUnweighted": [
        -1,
        -1,
        559.2,
        493.5,
        415.4,
        339,
        262.6,
        114.2,
        -1
      ]
    },
    "X": {
      "name": "X",
      "unicode": 88,
      "unicodeHex": "U+0058",
      "char": "X",
      "advanceWidth": 1454,
      "left": [
        -1,
        -1,
        127.4,
        235.8,
        344.2,
        452.6,
        354.1,
        135.7,
        -1
      ],
      "right": [
        -1,
        -1,
        83.5,
        191.9,
        300.3,
        408.7,
        412.4,
        182.2,
        -1
      ],
      "leftUnweighted": [
        -1,
        -1,
        127.4,
        352.4,
        534.7,
        526.8,
        354.1,
        135.7,
        -1
      ],
      "rightUnweighted": [
        -1,
        -1,
        83.5,
        297.1,
        469.3,
        571.7,
        412.4,
        182.2,
        -1
      ]
    },
    "Y": {
      "name": "Y",
      "unicode": 89,
      "unicodeHex": "U+0059",
      "char": "Y",
      "advanceWidth": 1374,
      "left": [
        -1,
        -1,
        457.5,
        553.6,
        445.2,
        336.8,
        228.4,
        120,
        -1
      ],
      "right": [
        -1,
        -1,
        411.5,
        554.8,
        446.4,
        338,
        229.6,
        121.2,
        -1
      ],
      "leftUnweighted": [
        -1,
        -1,
        457.5,
        612.4,
        597.9,
        471,
        322.4,
        120,
        -1
      ],
      "rightUnweighted": [
        -1,
        -1,
        411.5,
        566.4,
        553.9,
        444.1,
        315,
        121.2,
        -1
      ]
    },
    "Z": {
      "name": "Z",
      "unicode": 90,
      "unicodeHex": "U+005A",
      "char": "Z",
      "advanceWidth": 1314,
      "left": [
        -1,
        -1,
        99.5,
        219.4,
        399.7,
        303.7,
        195.3,
        86.9,
        -1
      ],
      "right": [
        -1,
        -1,
        102,
        102,
        210.4,
        318.8,
        286.2,
        130.7,
        -1
      ],
      "leftUnweighted": [
        -1,
        -1,
        99.5,
        219.4,
        399.7,
        581.8,
        273.5,
        86.9,
        -1
      ],
      "rightUnweighted": [
        -1,
        -1,
        102,
        102,
        581.9,
        464.6,
        286.2,
        130.7,
        -1
      ]
    },
    "Z.alt": {
      "name": "Z.alt",
      "unicode": null,
      "unicodeHex": null,
      "char": "Z.alt",
      "advanceWidth": 1687,
      "left": [
        -1,
        506.7,
        398.3,
        289.9,
        310.8,
        202.4,
        94,
        94,
        202.4
      ],
      "right": [
        -1,
        94,
        94,
        202.4,
        310.8,
        419.2,
        162.2,
        94,
        94
      ],
      "leftUnweighted": [
        -1,
        1515.3,
        531.9,
        289.9,
        583.4,
        878.2,
        94,
        94,
        1518.4
      ],
      "rightUnweighted": [
        -1,
        94,
        94,
        433.1,
        735.3,
        444.6,
        162.2,
        94,
        94
      ]
    },
    "a": {
      "name": "a",
      "unicode": 97,
      "unicodeHex": "U+0061",
      "char": "a",
      "advanceWidth": 856,
      "left": [
        -1,
        -1,
        131.4,
        181.3,
        289.7,
        198.4,
        -1,
        -1,
        -1
      ],
      "right": [
        -1,
        -1,
        49.4,
        157.8,
        170,
        200.7,
        -1,
        -1,
        -1
      ],
      "leftUnweighted": [
        -1,
        -1,
        131.4,
        181.3,
        303.5,
        198.4,
        -1,
        -1,
        -1
      ],
      "rightUnweighted": [
        -1,
        -1,
        49.4,
        167.7,
        170,
        200.7,
        -1,
        -1,
        -1
      ]
    },
    "ae": {
      "name": "ae",
      "unicode": 230,
      "unicodeHex": "U+00E6",
      "char": "ae",
      "advanceWidth": 1149,
      "left": [
        -1,
        -1,
        101.4,
        132.4,
        240.8,
        187.1,
        -1,
        -1,
        -1
      ],
      "right": [
        -1,
        -1,
        111.9,
        309.7,
        201.3,
        92.9,
        -1,
        -1,
        -1
      ],
      "leftUnweighted": [
        -1,
        -1,
        101.4,
        132.4,
        266.3,
        187.1,
        -1,
        -1,
        -1
      ],
      "rightUnweighted": [
        -1,
        -1,
        111.9,
        336.6,
        243.7,
        92.9,
        -1,
        -1,
        -1
      ]
    },
    "b": {
      "name": "b",
      "unicode": 98,
      "unicodeHex": "U+0062",
      "char": "b",
      "advanceWidth": 1055,
      "left": [
        -1,
        -1,
        261.4,
        153,
        153,
        153,
        153,
        87.8,
        141.4
      ],
      "right": [
        -1,
        -1,
        203.3,
        94.9,
        76.6,
        185,
        293.4,
        401.8,
        510.2
      ],
      "leftUnweighted": [
        -1,
        -1,
        265.2,
        153,
        153,
        153,
        153,
        87.8,
        141.4
      ],
      "rightUnweighted": [
        -1,
        -1,
        276.4,
        94.9,
        76.6,
        230.6,
        718,
        718,
        723.4
      ]
    },
    "c": {
      "name": "c",
      "unicode": 99,
      "unicodeHex": "U+0063",
      "char": "c",
      "advanceWidth": 891,
      "left": [
        -1,
        -1,
        193.1,
        84.7,
        86.3,
        194.7,
        -1,
        -1,
        -1
      ],
      "right": [
        -1,
        -1,
        139,
        308.7,
        200.3,
        91.9,
        -1,
        -1,
        -1
      ],
      "leftUnweighted": [
        -1,
        -1,
        216.1,
        84.7,
        86.3,
        232.4,
        -1,
        -1,
        -1
      ],
      "rightUnweighted": [
        -1,
        -1,
        139,
        430,
        564.1,
        91.9,
        -1,
        -1,
        -1
      ]
    },
    "d": {
      "name": "d",
      "unicode": 100,
      "unicodeHex": "U+0064",
      "char": "d",
      "advanceWidth": 1073,
      "left": [
        -1,
        -1,
        195.9,
        87.5,
        80.4,
        188.8,
        297.2,
        405.6,
        514
      ],
      "right": [
        -1,
        -1,
        83.1,
        158.7,
        170,
        170,
        170,
        170,
        170
      ],
      "leftUnweighted": [
        -1,
        -1,
        205.2,
        87.5,
        80.4,
        232.3,
        719,
        717.1,
        608.7
      ],
      "rightUnweighted": [
        -1,
        -1,
        83.1,
        158.7,
        170,
        170,
        170,
        170,
        170
      ]
    },
    "e": {
      "name": "e",
      "unicode": 101,
      "unicodeHex": "U+0065",
      "char": "e",
      "advanceWidth": 879,
      "left": [
        -1,
        -1,
        198.2,
        89.8,
        79.8,
        188.2,
        -1,
        -1,
        -1
      ],
      "right": [
        -1,
        -1,
        163.3,
        372.4,
        264,
        155.6,
        -1,
        -1,
        -1
      ],
      "leftUnweighted": [
        -1,
        -1,
        224.9,
        89.8,
        79.8,
        206.4,
        -1,
        -1,
        -1
      ],
      "rightUnweighted": [
        -1,
        -1,
        163.3,
        432.5,
        283.3,
        155.6,
        -1,
        -1,
        -1
      ]
    },
    "f": {
      "name": "f",
      "unicode": 102,
      "unicodeHex": "U+0066",
      "char": "f",
      "advanceWidth": 620,
      "left": [
        -1,
        -1,
        88,
        186.4,
        187,
        131.8,
        201.8,
        277.4,
        385.8
      ],
      "right": [
        -1,
        -1,
        150,
        248.4,
        180.2,
        71.8,
        -36.6,
        -145,
        -253.4
      ],
      "leftUnweighted": [
        -1,
        -1,
        88,
        186.4,
        187,
        131.8,
        201.8,
        277.4,
        445.1
      ],
      "rightUnweighted": [
        -1,
        -1,
        150,
        248.4,
        249,
        156.2,
        248.4,
        -22.8,
        -253.4
      ]
    },
    "g": {
      "name": "g",
      "unicode": 103,
      "unicodeHex": "U+0067",
      "char": "g",
      "advanceWidth": 1068,
      "left": [
        154.9,
        116.5,
        152.5,
        190.5,
        91.6,
        194.7,
        -1,
        -1,
        -1
      ],
      "right": [
        135.2,
        26.8,
        135.2,
        243.6,
        207.6,
        127.2,
        -1,
        -1,
        -1
      ],
      "leftUnweighted": [
        154.9,
        116.5,
        152.5,
        190.5,
        91.6,
        194.7,
        -1,
        -1,
        -1
      ],
      "rightUnweighted": [
        211.4,
        26.8,
        240.9,
        423.6,
        207.6,
        127.2,
        -1,
        -1,
        -1
      ]
    },
    "h": {
      "name": "h",
      "unicode": 104,
      "unicodeHex": "U+0068",
      "char": "h",
      "advanceWidth": 1076,
      "left": [
        -1,
        -1,
        71,
        169.4,
        170,
        170,
        170,
        104.3,
        161.3
      ],
      "right": [
        -1,
        -1,
        71,
        169.4,
        170,
        262.1,
        370.5,
        478.9,
        587.3
      ],
      "leftUnweighted": [
        -1,
        -1,
        71,
        169.4,
        170,
        170,
        170,
        104.3,
        161.3
      ],
      "rightUnweighted": [
        -1,
        -1,
        71,
        169.4,
        170,
        262.1,
        722,
        722,
        727.6
      ]
    },
    "i": {
      "name": "i",
      "unicode": 105,
      "unicodeHex": "U+0069",
      "char": "i",
      "advanceWidth": 541,
      "left": [
        -1,
        -1,
        88,
        186.4,
        171.2,
        110.5,
        191.5,
        161.9,
        -1
      ],
      "right": [
        -1,
        -1,
        71,
        169.4,
        170,
        171.2,
        206.9,
        177.8,
        -1
      ],
      "leftUnweighted": [
        -1,
        -1,
        88,
        186.4,
        171.2,
        110.5,
        191.5,
        161.9,
        -1
      ],
      "rightUnweighted": [
        -1,
        -1,
        71,
        169.4,
        170,
        171.2,
        206.9,
        177.8,
        -1
      ]
    },
    "dotlessi": {
      "name": "dotlessi",
      "unicode": 305,
      "unicodeHex": "U+0131",
      "char": "dotlessi",
      "advanceWidth": 541,
      "left": [
        -1,
        -1,
        88,
        186.4,
        171.2,
        110.5,
        -1,
        -1,
        -1
      ],
      "right": [
        -1,
        -1,
        71,
        169.4,
        170,
        171.2,
        -1,
        -1,
        -1
      ],
      "leftUnweighted": [
        -1,
        -1,
        88,
        186.4,
        171.2,
        110.5,
        -1,
        -1,
        -1
      ],
      "rightUnweighted": [
        -1,
        -1,
        71,
        169.4,
        170,
        171.2,
        -1,
        -1,
        -1
      ]
    },
    "j": {
      "name": "j",
      "unicode": 106,
      "unicodeHex": "U+006A",
      "char": "j",
      "advanceWidth": 507,
      "left": [
        -169.9,
        -61.5,
        46.9,
        155.3,
        154.2,
        93.5,
        174.5,
        144.9,
        -1
      ],
      "right": [
        326.6,
        218.2,
        163.9,
        153,
        153,
        154.2,
        189.9,
        160.8,
        -1
      ],
      "leftUnweighted": [
        -169.9,
        162.7,
        170,
        170,
        154.2,
        93.5,
        174.5,
        144.9,
        -1
      ],
      "rightUnweighted": [
        339.8,
        218.2,
        163.9,
        153,
        153,
        154.2,
        189.9,
        160.8,
        -1
      ]
    },
    "uni0237": {
      "name": "uni0237",
      "unicode": 567,
      "unicodeHex": "U+0237",
      "char": "uni0237",
      "advanceWidth": 507,
      "left": [
        -169.9,
        -61.5,
        46.9,
        155.3,
        154.2,
        93.5,
        -1,
        -1,
        -1
      ],
      "right": [
        326.6,
        218.2,
        163.9,
        153,
        153,
        154.2,
        -1,
        -1,
        -1
      ],
      "leftUnweighted": [
        -169.9,
        162.7,
        170,
        170,
        154.2,
        93.5,
        -1,
        -1,
        -1
      ],
      "rightUnweighted": [
        339.8,
        218.2,
        163.9,
        153,
        153,
        154.2,
        -1,
        -1,
        -1
      ]
    },
    "k": {
      "name": "k",
      "unicode": 107,
      "unicodeHex": "U+006B",
      "char": "k",
      "advanceWidth": 1044,
      "left": [
        -1,
        -1,
        71,
        169.4,
        170,
        170,
        170,
        104.3,
        161.3
      ],
      "right": [
        -1,
        -1,
        42.9,
        151.3,
        259.7,
        243.5,
        351.9,
        460.3,
        568.7
      ],
      "leftUnweighted": [
        -1,
        -1,
        71,
        169.4,
        170,
        170,
        170,
        104.3,
        161.3
      ],
      "rightUnweighted": [
        -1,
        -1,
        42.9,
        238.1,
        359.2,
        243.5,
        690,
        690,
        695.6
      ]
    },
    "l": {
      "name": "l",
      "unicode": 108,
      "unicodeHex": "U+006C",
      "char": "l",
      "advanceWidth": 524,
      "left": [
        -1,
        -1,
        71,
        169.4,
        170,
        170,
        170,
        104.3,
        161.3
      ],
      "right": [
        -1,
        -1,
        71,
        169.4,
        170,
        170,
        170,
        170,
        175.6
      ],
      "leftUnweighted": [
        -1,
        -1,
        71,
        169.4,
        170,
        170,
        170,
        104.3,
        161.3
      ],
      "rightUnweighted": [
        -1,
        -1,
        71,
        169.4,
        170,
        170,
        170,
        170,
        175.6
      ]
    },
    "m": {
      "name": "m",
      "unicode": 109,
      "unicodeHex": "U+006D",
      "char": "m",
      "advanceWidth": 1645,
      "left": [
        -1,
        -1,
        88,
        186.4,
        171.2,
        110.5,
        -1,
        -1,
        -1
      ],
      "right": [
        -1,
        -1,
        71,
        169.4,
        170,
        211,
        -1,
        -1,
        -1
      ],
      "leftUnweighted": [
        -1,
        -1,
        88,
        186.4,
        171.2,
        110.5,
        -1,
        -1,
        -1
      ],
      "rightUnweighted": [
        -1,
        -1,
        71,
        169.4,
        170,
        211,
        -1,
        -1,
        -1
      ]
    },
    "n": {
      "name": "n",
      "unicode": 110,
      "unicodeHex": "U+006E",
      "char": "n",
      "advanceWidth": 1093,
      "left": [
        -1,
        -1,
        81.7,
        185.8,
        171.2,
        132.1,
        -1,
        -1,
        -1
      ],
      "right": [
        -1,
        -1,
        64.7,
        168.8,
        170,
        225.1,
        -1,
        -1,
        -1
      ],
      "leftUnweighted": [
        -1,
        -1,
        81.7,
        185.8,
        171.2,
        132.1,
        -1,
        -1,
        -1
      ],
      "rightUnweighted": [
        -1,
        -1,
        64.7,
        168.8,
        170,
        225.1,
        -1,
        -1,
        -1
      ]
    },
    "o": {
      "name": "o",
      "unicode": 111,
      "unicodeHex": "U+006F",
      "char": "o",
      "advanceWidth": 1056,
      "left": [
        -1,
        -1,
        198.9,
        90.5,
        82.3,
        190.7,
        -1,
        -1,
        -1
      ],
      "right": [
        -1,
        -1,
        203.5,
        95.1,
        79.7,
        188.1,
        -1,
        -1,
        -1
      ],
      "leftUnweighted": [
        -1,
        -1,
        237.3,
        90.5,
        82.3,
        236.2,
        -1,
        -1,
        -1
      ],
      "rightUnweighted": [
        -1,
        -1,
        259.9,
        95.1,
        79.7,
        216.5,
        -1,
        -1,
        -1
      ]
    },
    "p": {
      "name": "p",
      "unicode": 112,
      "unicodeHex": "U+0070",
      "char": "p",
      "advanceWidth": 1066,
      "left": [
        110.8,
        170,
        170,
        170,
        142.7,
        114.5,
        -1,
        -1,
        -1
      ],
      "right": [
        428.6,
        320.2,
        211.8,
        103.4,
        73.5,
        174.7,
        -1,
        -1,
        -1
      ],
      "leftUnweighted": [
        110.8,
        170,
        170,
        170,
        142.7,
        114.5,
        -1,
        -1,
        -1
      ],
      "rightUnweighted": [
        650.1,
        712,
        394.6,
        103.4,
        73.5,
        174.7,
        -1,
        -1,
        -1
      ]
    },
    "q": {
      "name": "q",
      "unicode": 113,
      "unicodeHex": "U+0071",
      "char": "q",
      "advanceWidth": 1055,
      "left": [
        412.9,
        304.5,
        196.1,
        87.7,
        80.2,
        188.6,
        -1,
        -1,
        -1
      ],
      "right": [
        91.1,
        153,
        153,
        153,
        153,
        212.1,
        -1,
        -1,
        -1
      ],
      "leftUnweighted": [
        658.8,
        718,
        360,
        87.7,
        80.2,
        232.2,
        -1,
        -1,
        -1
      ],
      "rightUnweighted": [
        91.1,
        153,
        153,
        153,
        153,
        212.1,
        -1,
        -1,
        -1
      ]
    },
    "r": {
      "name": "r",
      "unicode": 114,
      "unicodeHex": "U+0072",
      "char": "r",
      "advanceWidth": 739,
      "left": [
        -1,
        -1,
        88,
        186.4,
        171.2,
        104.5,
        -1,
        -1,
        -1
      ],
      "right": [
        -1,
        -1,
        238.8,
        231.5,
        123.1,
        14.7,
        -1,
        -1,
        -1
      ],
      "leftUnweighted": [
        -1,
        -1,
        88,
        186.4,
        171.2,
        104.5,
        -1,
        -1,
        -1
      ],
      "rightUnweighted": [
        -1,
        -1,
        238.8,
        367.4,
        338,
        14.7,
        -1,
        -1,
        -1
      ]
    },
    "s": {
      "name": "s",
      "unicode": 115,
      "unicodeHex": "U+0073",
      "char": "s",
      "advanceWidth": 675,
      "left": [
        -1,
        -1,
        95.6,
        204,
        115.4,
        124.4,
        -1,
        -1,
        -1
      ],
      "right": [
        -1,
        -1,
        140.9,
        69.9,
        178.3,
        104.7,
        -1,
        -1,
        -1
      ],
      "leftUnweighted": [
        -1,
        -1,
        95.6,
        230.4,
        115.4,
        124.4,
        -1,
        -1,
        -1
      ],
      "rightUnweighted": [
        -1,
        -1,
        140.9,
        69.9,
        221.7,
        104.7,
        -1,
        -1,
        -1
      ]
    },
    "germandbls": {
      "name": "germandbls",
      "unicode": 223,
      "unicodeHex": "U+00DF",
      "char": "germandbls",
      "advanceWidth": 1053,
      "left": [
        -1,
        -1,
        39,
        137.4,
        138,
        101.2,
        152.8,
        228.4,
        336.8
      ],
      "right": [
        -1,
        -1,
        118.1,
        49,
        157.4,
        265.8,
        155.2,
        98.8,
        197.4
      ],
      "leftUnweighted": [
        -1,
        -1,
        39,
        137.4,
        138,
        101.2,
        152.8,
        228.4,
        396.1
      ],
      "rightUnweighted": [
        -1,
        -1,
        118.1,
        49,
        216.3,
        390.4,
        155.2,
        98.8,
        197.4
      ]
    },
    "longs": {
      "name": "longs",
      "unicode": 383,
      "unicodeHex": "U+017F",
      "char": "longs",
      "advanceWidth": 506,
      "left": [
        -1,
        -1,
        39,
        137.4,
        138,
        101.2,
        152.8,
        228.4,
        336.8
      ],
      "right": [
        -1,
        -1,
        85,
        183.4,
        115.2,
        6.8,
        -101.6,
        -210,
        -318.4
      ],
      "leftUnweighted": [
        -1,
        -1,
        39,
        137.4,
        138,
        101.2,
        152.8,
        228.4,
        396.1
      ],
      "rightUnweighted": [
        -1,
        -1,
        85,
        183.4,
        184,
        184,
        183.4,
        -87.8,
        -318.4
      ]
    },
    "t": {
      "name": "t",
      "unicode": 116,
      "unicodeHex": "U+0074",
      "char": "t",
      "advanceWidth": 632,
      "left": [
        -1,
        -1,
        187.2,
        153,
        153,
        116.2,
        211.2,
        -1,
        -1
      ],
      "right": [
        -1,
        -1,
        73.3,
        181.7,
        290.1,
        183.8,
        292.2,
        -1,
        -1
      ],
      "leftUnweighted": [
        -1,
        -1,
        187.2,
        153,
        153,
        116.2,
        211.2,
        -1,
        -1
      ],
      "rightUnweighted": [
        -1,
        -1,
        73.3,
        293,
        295,
        183.8,
        303.5,
        -1,
        -1
      ]
    },
    "u": {
      "name": "u",
      "unicode": 117,
      "unicodeHex": "U+0075",
      "char": "u",
      "advanceWidth": 1093,
      "left": [
        -1,
        -1,
        228.7,
        170.3,
        170,
        97.7,
        -1,
        -1,
        -1
      ],
      "right": [
        -1,
        -1,
        87.6,
        186.2,
        187,
        187,
        -1,
        -1,
        -1
      ],
      "leftUnweighted": [
        -1,
        -1,
        228.7,
        170.3,
        170,
        97.7,
        -1,
        -1,
        -1
      ],
      "rightUnweighted": [
        -1,
        -1,
        87.6,
        186.2,
        187,
        187,
        -1,
        -1,
        -1
      ]
    },
    "v": {
      "name": "v",
      "unicode": 118,
      "unicodeHex": "U+0076",
      "char": "v",
      "advanceWidth": 966,
      "left": [
        -1,
        -1,
        394.8,
        286.4,
        178,
        69.6,
        -1,
        -1,
        -1
      ],
      "right": [
        -1,
        -1,
        395.7,
        287.3,
        178.9,
        70.5,
        -1,
        -1,
        -1
      ],
      "leftUnweighted": [
        -1,
        -1,
        411.3,
        320.8,
        214.4,
        69.6,
        -1,
        -1,
        -1
      ],
      "rightUnweighted": [
        -1,
        -1,
        396.1,
        311.1,
        211.7,
        70.5,
        -1,
        -1,
        -1
      ]
    },
    "w": {
      "name": "w",
      "unicode": 119,
      "unicodeHex": "U+0077",
      "char": "w",
      "advanceWidth": 1471,
      "left": [
        -1,
        -1,
        394.8,
        286.4,
        178,
        69.6,
        -1,
        -1,
        -1
      ],
      "right": [
        -1,
        -1,
        357.9,
        290.9,
        183.3,
        74.9,
        -1,
        -1,
        -1
      ],
      "leftUnweighted": [
        -1,
        -1,
        411.3,
        320.8,
        214.4,
        69.6,
        -1,
        -1,
        -1
      ],
      "rightUnweighted": [
        -1,
        -1,
        357.9,
        290.9,
        212.6,
        74.9,
        -1,
        -1,
        -1
      ]
    },
    "x": {
      "name": "x",
      "unicode": 120,
      "unicodeHex": "U+0078",
      "char": "x",
      "advanceWidth": 957,
      "left": [
        -1,
        -1,
        78.1,
        288.7,
        180.4,
        72,
        -1,
        -1,
        -1
      ],
      "right": [
        -1,
        -1,
        39.2,
        147.6,
        256,
        122.8,
        -1,
        -1,
        -1
      ],
      "leftUnweighted": [
        -1,
        -1,
        78.1,
        288.7,
        277.2,
        72,
        -1,
        -1,
        -1
      ],
      "rightUnweighted": [
        -1,
        -1,
        39.2,
        240.9,
        328.4,
        122.8,
        -1,
        -1,
        -1
      ]
    },
    "y": {
      "name": "y",
      "unicode": 121,
      "unicodeHex": "U+0079",
      "char": "y",
      "advanceWidth": 1057,
      "left": [
        36.6,
        145,
        253.4,
        313,
        201.6,
        58.5,
        -1,
        -1,
        -1
      ],
      "right": [
        621.2,
        512.8,
        404.4,
        296,
        187.6,
        79.2,
        -1,
        -1,
        -1
      ],
      "leftUnweighted": [
        36.6,
        320.2,
        405,
        313,
        201.6,
        58.5,
        -1,
        -1,
        -1
      ],
      "rightUnweighted": [
        766,
        621.9,
        494.8,
        370.4,
        247.7,
        79.2,
        -1,
        -1,
        -1
      ]
    },
    "z": {
      "name": "z",
      "unicode": 122,
      "unicodeHex": "U+007A",
      "char": "z",
      "advanceWidth": 870,
      "left": [
        -1,
        -1,
        120.5,
        230.7,
        190.3,
        81.9,
        -1,
        -1,
        -1
      ],
      "right": [
        -1,
        -1,
        68,
        176.4,
        242.7,
        97.2,
        -1,
        -1,
        -1
      ],
      "leftUnweighted": [
        -1,
        -1,
        120.5,
        230.7,
        315.8,
        81.9,
        -1,
        -1,
        -1
      ],
      "rightUnweighted": [
        -1,
        -1,
        68,
        217,
        242.7,
        97.2,
        -1,
        -1,
        -1
      ]
    },
    "s.fina": {
      "name": "s.fina",
      "unicode": null,
      "unicodeHex": null,
      "char": "s.fina",
      "advanceWidth": 598,
      "left": [
        -1,
        -1,
        57.1,
        154.7,
        113,
        123,
        -1,
        -1,
        -1
      ],
      "right": [
        -1,
        -1,
        87.5,
        37.1,
        145.5,
        54.8,
        -1,
        -1,
        -1
      ],
      "leftUnweighted": [
        -1,
        -1,
        57.1,
        154.7,
        113,
        123,
        -1,
        -1,
        -1
      ],
      "rightUnweighted": [
        -1,
        -1,
        87.5,
        37.1,
        173.8,
        54.8,
        -1,
        -1,
        -1
      ]
    },
    "c_t": {
      "name": "c_t",
      "unicode": null,
      "unicodeHex": null,
      "char": "c_t",
      "advanceWidth": 1523,
      "left": [
        -1,
        -1,
        193.1,
        84.7,
        86.4,
        194.8,
        303.2,
        411.6,
        -1
      ],
      "right": [
        -1,
        -1,
        73.3,
        181.7,
        290.1,
        183.8,
        292.2,
        400.6,
        -1
      ],
      "leftUnweighted": [
        -1,
        -1,
        216.1,
        84.7,
        86.4,
        260.7,
        532.7,
        662.5,
        -1
      ],
      "rightUnweighted": [
        -1,
        -1,
        73.3,
        293,
        295,
        183.8,
        309.1,
        441.4,
        -1
      ]
    },
    "s_i": {
      "name": "s_i",
      "unicode": null,
      "unicodeHex": null,
      "char": "s_i",
      "advanceWidth": 1047,
      "left": [
        -1,
        -1,
        39,
        137.4,
        138,
        101.2,
        158.3,
        266.7,
        375.1
      ],
      "right": [
        -1,
        -1,
        71,
        169.4,
        170,
        226.6,
        335,
        205.8,
        256.2
      ],
      "leftUnweighted": [
        -1,
        -1,
        39,
        137.4,
        138,
        101.2,
        158.3,
        279.2,
        512.4
      ],
      "rightUnweighted": [
        -1,
        -1,
        71,
        169.4,
        170,
        226.6,
        723,
        205.8,
        256.2
      ]
    },
    "s_s": {
      "name": "s_s",
      "unicode": null,
      "unicodeHex": null,
      "char": "s_s",
      "advanceWidth": 1012,
      "left": [
        -1,
        -1,
        39,
        137.4,
        138,
        101.2,
        151.7,
        237.6,
        346
      ],
      "right": [
        -1,
        -1,
        85,
        183.4,
        115.2,
        6.8,
        -101.6,
        -210,
        -318.4
      ],
      "leftUnweighted": [
        -1,
        -1,
        39,
        137.4,
        138,
        101.2,
        151.7,
        237.6,
        720.3
      ],
      "rightUnweighted": [
        -1,
        -1,
        85,
        183.4,
        184,
        184,
        183.4,
        -87.8,
        -318.4
      ]
    },
    "s_t": {
      "name": "s_t",
      "unicode": null,
      "unicodeHex": null,
      "char": "s_t",
      "advanceWidth": 1136,
      "left": [
        -1,
        -1,
        39,
        137.4,
        138,
        101.2,
        154.4,
        250.1,
        358.5
      ],
      "right": [
        -1,
        -1,
        71.3,
        179.7,
        288.1,
        181.8,
        290.2,
        293,
        345
      ],
      "leftUnweighted": [
        -1,
        -1,
        39,
        137.4,
        138,
        101.2,
        154.4,
        250.1,
        446.3
      ],
      "rightUnweighted": [
        -1,
        -1,
        71.3,
        291,
        293,
        181.8,
        293,
        293,
        345
      ]
    },
    "zero": {
      "name": "zero",
      "unicode": 48,
      "unicodeHex": "U+0030",
      "char": "zero",
      "advanceWidth": 1156,
      "left": [
        -1,
        -1,
        242,
        133.6,
        70.5,
        65.4,
        112.8,
        221.2,
        -1
      ],
      "right": [
        -1,
        -1,
        255.6,
        147.2,
        74.3,
        65.2,
        104.9,
        213.3,
        -1
      ],
      "leftUnweighted": [
        -1,
        -1,
        294.7,
        133.6,
        70.5,
        65.4,
        112.8,
        280.1,
        -1
      ],
      "rightUnweighted": [
        -1,
        -1,
        330.8,
        147.2,
        74.3,
        65.2,
        104.9,
        251.8,
        -1
      ]
    },
    "one": {
      "name": "one",
      "unicode": 49,
      "unicodeHex": "U+0031",
      "char": "one",
      "advanceWidth": 1156,
      "left": [
        -1,
        -1,
        301.4,
        500.1,
        501,
        501,
        399.2,
        290.8,
        399.2
      ],
      "right": [
        -1,
        -1,
        264.4,
        372.8,
        464,
        464,
        464,
        464,
        481.6
      ],
      "leftUnweighted": [
        -1,
        -1,
        301.4,
        500.1,
        501,
        501,
        471.6,
        290.8,
        589.5
      ],
      "rightUnweighted": [
        -1,
        -1,
        264.4,
        463.1,
        464,
        464,
        464,
        464,
        481.6
      ]
    },
    "two": {
      "name": "two",
      "unicode": 50,
      "unicodeHex": "U+0032",
      "char": "two",
      "advanceWidth": 1156,
      "left": [
        -1,
        -1,
        115.3,
        223.7,
        332.1,
        440.5,
        439.1,
        278,
        -1
      ],
      "right": [
        -1,
        -1,
        162,
        254.4,
        362.8,
        288.7,
        227.9,
        319.4,
        -1
      ],
      "leftUnweighted": [
        -1,
        -1,
        115.3,
        234.2,
        468.2,
        641.8,
        439.1,
        278,
        -1
      ],
      "rightUnweighted": [
        -1,
        -1,
        162,
        254.4,
        479.7,
        288.7,
        227.9,
        319.4,
        -1
      ]
    },
    "three": {
      "name": "three",
      "unicode": 51,
      "unicodeHex": "U+0033",
      "char": "three",
      "advanceWidth": 1156,
      "left": [
        -1,
        -1,
        282.4,
        174,
        282.4,
        390.8,
        499.2,
        297,
        -1
      ],
      "right": [
        -1,
        -1,
        273.1,
        164.7,
        158.8,
        267.2,
        263.5,
        298.8,
        -1
      ],
      "leftUnweighted": [
        -1,
        -1,
        299.6,
        174,
        719.8,
        518,
        499.2,
        297,
        -1
      ],
      "rightUnweighted": [
        -1,
        -1,
        323.1,
        164.7,
        158.8,
        313.8,
        263.5,
        298.8,
        -1
      ]
    },
    "four": {
      "name": "four",
      "unicode": 52,
      "unicodeHex": "U+0034",
      "char": "four",
      "advanceWidth": 1156,
      "left": [
        -1,
        -1,
        311.4,
        203,
        94.6,
        203,
        311.4,
        419.8,
        -1
      ],
      "right": [
        -1,
        -1,
        170.4,
        257.9,
        187,
        295.4,
        306,
        306,
        -1
      ],
      "leftUnweighted": [
        -1,
        -1,
        525.4,
        538.9,
        94.6,
        256.6,
        420.7,
        582.4,
        -1
      ],
      "rightUnweighted": [
        -1,
        -1,
        170.4,
        257.9,
        187,
        306,
        306,
        306,
        -1
      ]
    },
    "five": {
      "name": "five",
      "unicode": 53,
      "unicodeHex": "U+0035",
      "char": "five",
      "advanceWidth": 1156,
      "left": [
        -1,
        -1,
        277.9,
        169.5,
        277.9,
        306.7,
        256.6,
        290.7,
        -1
      ],
      "right": [
        -1,
        -1,
        284.2,
        175.8,
        152.1,
        260.5,
        368.9,
        197,
        -1
      ],
      "leftUnweighted": [
        -1,
        -1,
        308.2,
        169.5,
        669,
        306.7,
        256.6,
        290.7,
        -1
      ],
      "rightUnweighted": [
        -1,
        -1,
        335.2,
        175.8,
        152.1,
        278.5,
        468.8,
        197,
        -1
      ]
    },
    "six": {
      "name": "six",
      "unicode": 54,
      "unicodeHex": "U+0036",
      "char": "six",
      "advanceWidth": 1156,
      "left": [
        -1,
        -1,
        252.7,
        144.3,
        86.6,
        104.5,
        207.3,
        315.7,
        424.1
      ],
      "right": [
        -1,
        -1,
        243.4,
        135,
        114.9,
        223.3,
        331.7,
        373.4,
        236.5
      ],
      "leftUnweighted": [
        -1,
        -1,
        317.1,
        144.3,
        86.6,
        104.5,
        207.3,
        466.6,
        796.6
      ],
      "rightUnweighted": [
        -1,
        -1,
        299.5,
        135,
        114.9,
        308.2,
        736.5,
        373.4,
        236.5
      ]
    },
    "seven": {
      "name": "seven",
      "unicode": 55,
      "unicodeHex": "U+0037",
      "char": "seven",
      "advanceWidth": 1156,
      "left": [
        -1,
        -1,
        325.3,
        386.2,
        457.2,
        348.8,
        240.4,
        132,
        -1
      ],
      "right": [
        -1,
        -1,
        646.9,
        548.4,
        440.6,
        332.8,
        224.9,
        151.5,
        -1
      ],
      "leftUnweighted": [
        -1,
        -1,
        325.3,
        386.2,
        513.5,
        639.8,
        435.4,
        132,
        -1
      ],
      "rightUnweighted": [
        -1,
        -1,
        646.9,
        548.4,
        440.6,
        332.8,
        224.9,
        151.5,
        -1
      ]
    },
    "eight": {
      "name": "eight",
      "unicode": 56,
      "unicodeHex": "U+0038",
      "char": "eight",
      "advanceWidth": 1156,
      "left": [
        -1,
        -1,
        215.6,
        107.2,
        127.8,
        236.2,
        150.2,
        244.2,
        352.6
      ],
      "right": [
        -1,
        -1,
        229.2,
        120.8,
        107.6,
        216,
        206,
        256.9,
        365.3
      ],
      "leftUnweighted": [
        -1,
        -1,
        259.9,
        107.2,
        127.8,
        261.7,
        150.2,
        244.2,
        512.1
      ],
      "rightUnweighted": [
        -1,
        -1,
        299.4,
        120.8,
        107.6,
        273.1,
        206,
        256.9,
        490.1
      ]
    },
    "nine": {
      "name": "nine",
      "unicode": 57,
      "unicodeHex": "U+0039",
      "char": "nine",
      "advanceWidth": 1156,
      "left": [
        -1,
        -1,
        252.9,
        349.9,
        241.5,
        133.1,
        101.8,
        210.2,
        318.6
      ],
      "right": [
        -1,
        -1,
        360.2,
        251.8,
        143.4,
        96.8,
        120.7,
        229.1,
        337.5
      ],
      "leftUnweighted": [
        -1,
        -1,
        252.9,
        623.6,
        542.5,
        133.1,
        101.8,
        222.1,
        435.1
      ],
      "rightUnweighted": [
        -1,
        -1,
        586.1,
        292.6,
        143.4,
        96.8,
        120.7,
        260.6,
        471.6
      ]
    },
    "zero.osf": {
      "name": "zero.osf",
      "unicode": null,
      "unicodeHex": null,
      "char": "zero.osf",
      "advanceWidth": 1058,
      "left": [
        -1,
        -1,
        205.1,
        96.7,
        76.8,
        185.2,
        -1,
        -1,
        -1
      ],
      "right": [
        -1,
        -1,
        199.2,
        90.8,
        79.8,
        188.2,
        -1,
        -1,
        -1
      ],
      "leftUnweighted": [
        -1,
        -1,
        250.6,
        96.7,
        76.8,
        224.8,
        -1,
        -1,
        -1
      ],
      "rightUnweighted": [
        -1,
        -1,
        239.4,
        90.8,
        79.8,
        228.1,
        -1,
        -1,
        -1
      ]
    },
    "one.osf": {
      "name": "one.osf",
      "unicode": null,
      "unicodeHex": null,
      "char": "one.osf",
      "advanceWidth": 626,
      "left": [
        -1,
        -1,
        117.9,
        212.7,
        213,
        145.6,
        -1,
        -1,
        -1
      ],
      "right": [
        -1,
        -1,
        137.9,
        232.7,
        233,
        165.6,
        -1,
        -1,
        -1
      ],
      "leftUnweighted": [
        -1,
        -1,
        117.9,
        212.7,
        213,
        145.6,
        -1,
        -1,
        -1
      ],
      "rightUnweighted": [
        -1,
        -1,
        137.9,
        232.7,
        233,
        165.6,
        -1,
        -1,
        -1
      ]
    },
    "two.osf": {
      "name": "two.osf",
      "unicode": null,
      "unicodeHex": null,
      "char": "two.osf",
      "advanceWidth": 736,
      "left": [
        -1,
        -1,
        35.2,
        143.6,
        252,
        146.8,
        -1,
        -1,
        -1
      ],
      "right": [
        -1,
        -1,
        30,
        138.4,
        131.6,
        154.1,
        -1,
        -1,
        -1
      ],
      "leftUnweighted": [
        -1,
        -1,
        35.2,
        223.5,
        381.9,
        146.8,
        -1,
        -1,
        -1
      ],
      "rightUnweighted": [
        -1,
        -1,
        30,
        281.4,
        131.6,
        154.1,
        -1,
        -1,
        -1
      ]
    },
    "three.osf": {
      "name": "three.osf",
      "unicode": null,
      "unicodeHex": null,
      "char": "three.osf",
      "advanceWidth": 730,
      "left": [
        82,
        190.4,
        298.8,
        180.9,
        289.3,
        103.2,
        -1,
        -1,
        -1
      ],
      "right": [
        260.5,
        152.1,
        57.2,
        163.2,
        188.2,
        218.1,
        -1,
        -1,
        -1
      ],
      "leftUnweighted": [
        82,
        350.4,
        477,
        180.9,
        309,
        103.2,
        -1,
        -1,
        -1
      ],
      "rightUnweighted": [
        390.1,
        152.1,
        57.2,
        163.2,
        188.2,
        218.1,
        -1,
        -1,
        -1
      ]
    },
    "four.osf": {
      "name": "four.osf",
      "unicode": null,
      "unicodeHex": null,
      "char": "four.osf",
      "advanceWidth": 1104,
      "left": [
        529.1,
        420.7,
        312.3,
        203.9,
        312.3,
        420.7,
        529.1,
        -1,
        -1
      ],
      "right": [
        283.2,
        246.5,
        138.1,
        246.5,
        290.4,
        292.2,
        293.6,
        -1,
        -1
      ],
      "leftUnweighted": [
        633.1,
        633.8,
        338.3,
        203.9,
        417.7,
        633.3,
        771.6,
        -1,
        -1
      ],
      "rightUnweighted": [
        283.2,
        284.7,
        138.1,
        258.9,
        290.4,
        292.2,
        293.6,
        -1,
        -1
      ]
    },
    "five.osf": {
      "name": "five.osf",
      "unicode": null,
      "unicodeHex": null,
      "char": "five.osf",
      "advanceWidth": 836,
      "left": [
        160,
        356,
        315.3,
        206.9,
        98.5,
        206.9,
        -1,
        -1,
        -1
      ],
      "right": [
        370,
        261.6,
        153.2,
        153.1,
        230.2,
        121.8,
        -1,
        -1,
        -1
      ],
      "leftUnweighted": [
        160,
        356,
        513.2,
        230,
        98.5,
        309,
        -1,
        -1,
        -1
      ],
      "rightUnweighted": [
        538.2,
        292,
        153.2,
        153.1,
        485.5,
        121.8,
        -1,
        -1,
        -1
      ]
    },
    "six.osf": {
      "name": "six.osf",
      "unicode": null,
      "unicodeHex": null,
      "char": "six.osf",
      "advanceWidth": 932,
      "left": [
        -1,
        -1,
        167.9,
        59.5,
        74.5,
        182.9,
        291.3,
        -1,
        -1
      ],
      "right": [
        -1,
        -1,
        257,
        148.6,
        212.3,
        133.7,
        25.3,
        -1,
        -1
      ],
      "leftUnweighted": [
        -1,
        -1,
        176.9,
        59.5,
        74.5,
        273.5,
        692.4,
        -1,
        -1
      ],
      "rightUnweighted": [
        -1,
        -1,
        273.1,
        148.6,
        212.3,
        365.6,
        25.3,
        -1,
        -1
      ]
    },
    "seven.osf": {
      "name": "seven.osf",
      "unicode": null,
      "unicodeHex": null,
      "char": "seven.osf",
      "advanceWidth": 1116,
      "left": [
        -1,
        182.2,
        288.9,
        341.3,
        232.9,
        124.5,
        -1,
        -1,
        -1
      ],
      "right": [
        -1,
        545.3,
        436.9,
        328.5,
        220.1,
        111.7,
        -1,
        -1,
        -1
      ],
      "leftUnweighted": [
        -1,
        182.2,
        288.9,
        489.8,
        693.3,
        124.5,
        -1,
        -1,
        -1
      ],
      "rightUnweighted": [
        -1,
        800.7,
        650.7,
        465.2,
        279.5,
        111.7,
        -1,
        -1,
        -1
      ]
    },
    "eight.osf": {
      "name": "eight.osf",
      "unicode": null,
      "unicodeHex": null,
      "char": "eight.osf",
      "advanceWidth": 874,
      "left": [
        -1,
        -1,
        167.3,
        73.5,
        181.9,
        110.1,
        148.7,
        257.1,
        -1
      ],
      "right": [
        -1,
        -1,
        171.6,
        77.4,
        185.8,
        162,
        162.2,
        270.6,
        -1
      ],
      "leftUnweighted": [
        -1,
        -1,
        167.3,
        73.5,
        206.2,
        110.1,
        148.7,
        375.9,
        -1
      ],
      "rightUnweighted": [
        -1,
        -1,
        171.6,
        77.4,
        206.4,
        162,
        162.2,
        367,
        -1
      ]
    },
    "nine.osf": {
      "name": "nine.osf",
      "unicode": null,
      "unicodeHex": null,
      "char": "nine.osf",
      "advanceWidth": 900,
      "left": [
        84.3,
        246.9,
        186.2,
        77.8,
        128,
        236.4,
        -1,
        -1,
        -1
      ],
      "right": [
        372.6,
        264.2,
        155.8,
        85.2,
        138,
        246.4,
        -1,
        -1,
        -1
      ],
      "leftUnweighted": [
        84.3,
        246.9,
        345.8,
        77.8,
        128,
        317.6,
        -1,
        -1,
        -1
      ],
      "rightUnweighted": [
        782.3,
        421.5,
        155.8,
        85.2,
        138,
        297.4,
        -1,
        -1,
        -1
      ]
    },
    "period": {
      "name": "period",
      "unicode": 46,
      "unicodeHex": "U+002E",
      "char": "period",
      "advanceWidth": 463,
      "left": [
        -1,
        -1,
        119.8,
        143,
        -1,
        -1,
        -1,
        -1,
        -1
      ],
      "right": [
        -1,
        -1,
        119.5,
        142.1,
        -1,
        -1,
        -1,
        -1,
        -1
      ],
      "leftUnweighted": [
        -1,
        -1,
        119.8,
        143,
        -1,
        -1,
        -1,
        -1,
        -1
      ],
      "rightUnweighted": [
        -1,
        -1,
        119.5,
        142.1,
        -1,
        -1,
        -1,
        -1,
        -1
      ]
    },
    "comma": {
      "name": "comma",
      "unicode": 44,
      "unicodeHex": "U+002C",
      "char": "comma",
      "advanceWidth": 520,
      "left": [
        75,
        183.4,
        150.9,
        141.1,
        -1,
        -1,
        -1,
        -1,
        -1
      ],
      "right": [
        295.2,
        186.8,
        99.7,
        162,
        -1,
        -1,
        -1,
        -1,
        -1
      ],
      "leftUnweighted": [
        75,
        200.6,
        150.9,
        141.1,
        -1,
        -1,
        -1,
        -1,
        -1
      ],
      "rightUnweighted": [
        351,
        186.8,
        99.7,
        162,
        -1,
        -1,
        -1,
        -1,
        -1
      ]
    },
    "colon": {
      "name": "colon",
      "unicode": 58,
      "unicodeHex": "U+003A",
      "char": "colon",
      "advanceWidth": 509,
      "left": [
        -1,
        -1,
        121.6,
        -1,
        174.7,
        172.6,
        -1,
        -1,
        -1
      ],
      "right": [
        -1,
        -1,
        175.4,
        -1,
        120.6,
        118.1,
        -1,
        -1,
        -1
      ],
      "leftUnweighted": [
        -1,
        -1,
        121.6,
        -1,
        174.7,
        172.6,
        -1,
        -1,
        -1
      ],
      "rightUnweighted": [
        -1,
        -1,
        175.4,
        -1,
        120.6,
        118.1,
        -1,
        -1,
        -1
      ]
    },
    "semicolon": {
      "name": "semicolon",
      "unicode": 59,
      "unicodeHex": "U+003B",
      "char": "semicolon",
      "advanceWidth": 537,
      "left": [
        95.6,
        204,
        148.5,
        176.3,
        215,
        197.7,
        -1,
        -1,
        -1
      ],
      "right": [
        262.3,
        153.9,
        107.1,
        186.2,
        126.7,
        110.3,
        -1,
        -1,
        -1
      ],
      "leftUnweighted": [
        95.6,
        245.3,
        148.5,
        176.3,
        215,
        197.7,
        -1,
        -1,
        -1
      ],
      "rightUnweighted": [
        316.1,
        153.9,
        107.1,
        186.2,
        126.7,
        110.3,
        -1,
        -1,
        -1
      ]
    },
    "periodcentered": {
      "name": "periodcentered",
      "unicode": 183,
      "unicodeHex": "U+00B7",
      "char": "periodcentered",
      "advanceWidth": 552,
      "left": [
        -1,
        -1,
        -1,
        -1,
        185.8,
        209.2,
        -1,
        -1,
        -1
      ],
      "right": [
        -1,
        -1,
        -1,
        -1,
        126.5,
        149.4,
        -1,
        -1,
        -1
      ],
      "leftUnweighted": [
        -1,
        -1,
        -1,
        -1,
        185.8,
        209.2,
        -1,
        -1,
        -1
      ],
      "rightUnweighted": [
        -1,
        -1,
        -1,
        -1,
        126.5,
        149.4,
        -1,
        -1,
        -1
      ]
    },
    "hyphen": {
      "name": "hyphen",
      "unicode": 45,
      "unicodeHex": "U+002D",
      "char": "hyphen",
      "advanceWidth": 552,
      "left": [
        -1,
        -1,
        -1,
        -1,
        46,
        -1,
        -1,
        -1,
        -1
      ],
      "right": [
        -1,
        -1,
        -1,
        -1,
        46,
        -1,
        -1,
        -1,
        -1
      ],
      "leftUnweighted": [
        -1,
        -1,
        -1,
        -1,
        46,
        -1,
        -1,
        -1,
        -1
      ],
      "rightUnweighted": [
        -1,
        -1,
        -1,
        -1,
        46,
        -1,
        -1,
        -1,
        -1
      ]
    },
    "endash": {
      "name": "endash",
      "unicode": 8211,
      "unicodeHex": "U+2013",
      "char": "endash",
      "advanceWidth": 1200,
      "left": [
        -1,
        -1,
        -1,
        -1,
        46,
        -1,
        -1,
        -1,
        -1
      ],
      "right": [
        -1,
        -1,
        -1,
        -1,
        46,
        -1,
        -1,
        -1,
        -1
      ],
      "leftUnweighted": [
        -1,
        -1,
        -1,
        -1,
        46,
        -1,
        -1,
        -1,
        -1
      ],
      "rightUnweighted": [
        -1,
        -1,
        -1,
        -1,
        46,
        -1,
        -1,
        -1,
        -1
      ]
    },
    "emdash": {
      "name": "emdash",
      "unicode": 8212,
      "unicodeHex": "U+2014",
      "char": "emdash",
      "advanceWidth": 1200,
      "left": [
        -1,
        -1,
        -1,
        -1,
        46,
        -1,
        -1,
        -1,
        -1
      ],
      "right": [
        -1,
        -1,
        -1,
        -1,
        46,
        -1,
        -1,
        -1,
        -1
      ],
      "leftUnweighted": [
        -1,
        -1,
        -1,
        -1,
        46,
        -1,
        -1,
        -1,
        -1
      ],
      "rightUnweighted": [
        -1,
        -1,
        -1,
        -1,
        46,
        -1,
        -1,
        -1,
        -1
      ]
    },
    "underscore": {
      "name": "underscore",
      "unicode": 95,
      "unicodeHex": "U+005F",
      "char": "underscore",
      "advanceWidth": 1200,
      "left": [
        0,
        0,
        -1,
        -1,
        -1,
        -1,
        -1,
        -1,
        -1
      ],
      "right": [
        0,
        0,
        -1,
        -1,
        -1,
        -1,
        -1,
        -1,
        -1
      ],
      "leftUnweighted": [
        0,
        0,
        -1,
        -1,
        -1,
        -1,
        -1,
        -1,
        -1
      ],
      "rightUnweighted": [
        0,
        0,
        -1,
        -1,
        -1,
        -1,
        -1,
        -1,
        -1
      ]
    },
    "ampersand": {
      "name": "ampersand",
      "unicode": 38,
      "unicodeHex": "U+0026",
      "char": "ampersand",
      "advanceWidth": 1760,
      "left": [
        -1,
        -1,
        189.1,
        80.7,
        94.4,
        202.8,
        311.2,
        289.5,
        397.9
      ],
      "right": [
        -1,
        -1,
        160.2,
        268.6,
        377,
        441.4,
        473.9,
        582.3,
        690.7
      ],
      "leftUnweighted": [
        -1,
        -1,
        253.3,
        80.7,
        94.4,
        299.3,
        319.8,
        289.5,
        478.8
      ],
      "rightUnweighted": [
        -1,
        -1,
        160.2,
        346.5,
        592.4,
        441.4,
        473.9,
        892.7,
        1049.3
      ]
    },
    "bar": {
      "name": "bar",
      "unicode": 124,
      "unicodeHex": "U+007C",
      "char": "verticalbar",
      "advanceWidth": 276,
      "left": [
        92,
        92,
        92,
        92,
        92,
        92,
        92,
        92,
        92
      ],
      "right": [
        92,
        92,
        92,
        92,
        92,
        92,
        92,
        92,
        92
      ],
      "leftUnweighted": [
        92,
        92,
        92,
        92,
        92,
        92,
        92,
        92,
        92
      ],
      "rightUnweighted": [
        92,
        92,
        92,
        92,
        92,
        92,
        92,
        92,
        92
      ]
    }
  }
}